setup.cfg
setup.py
django_elastimorphic.egg-info/PKG-INFO
django_elastimorphic.egg-info/SOURCES.txt
django_elastimorphic.egg-info/dependency_links.txt
django_elastimorphic.egg-info/requires.txt
django_elastimorphic.egg-info/top_level.txt
elastimorphic/__init__.py
elastimorphic/apps.py
elastimorphic/base.py
elastimorphic/models.py
elastimorphic/serializers.py
elastimorphic/conf/__init__.py
elastimorphic/conf/defaults.py
elastimorphic/management/__init__.py
elastimorphic/management/commands/__init__.py
elastimorphic/management/commands/bulk_index.py
elastimorphic/management/commands/es_swap_aliases.py
elastimorphic/management/commands/synces.py
elastimorphic/mappings/__init__.py
elastimorphic/mappings/doctype.py
elastimorphic/mappings/fields.py
elastimorphic/tests/__init__.py
elastimorphic/tests/base.py
elastimorphic/tests/drf/__init__.py
elastimorphic/tests/drf/test_serializers.py
elastimorphic/tests/testapp/__init__.py
elastimorphic/tests/testapp/models.py
elastimorphic/tests/testapp/serializers.py
elastimorphic/tests/testdeclarative/__init__.py
elastimorphic/tests/testdeclarative/models.py