Metadata-Version: 1.0
Name: django-elastimorphic
Version: 0.1.8
Summary: A marriage of django-polymorphic and elasticutils.
Home-page: https://github.com/theonion/django-elastimorphic
Author: Onion Tech Team
Author-email: tech@theonion.com
License: MIT
Platform: UNKNOWN
